fermihalos/__init__.py
fermihalos/model.py
fermihalos/rar_class.py
fermihalos-0.1.2.dist-info/licenses/LICENSE
fermihalos-0.1.2.dist-info/METADATA
fermihalos-0.1.2.dist-info/WHEEL
fermihalos-0.1.2.dist-info/top_level.txt
fermihalos-0.1.2.dist-info/RECORD
