Metadata-Version: 2.4
Name: fermihalos
Version: 0.1.2
Summary: An extended RAR model for dark matter halo astrophysics.
Home-page: https://github.com/Santiq22/FermiHalos
Author: RAR collaboration
Author-email: Santiago Collazo <scollazo@fcaglp.unlp.edu.ar>, Martín Federico Mestre Citrinovitz <mmestre@fcaglp.unlp.edu.ar>
License-Expression: MIT
Project-URL: homepage, https://santiq22.github.io/FermiHalos/
Project-URL: documentation, https://santiq22.github.io/FermiHalos/
Project-URL: source, https://github.com/Santiq22/FermiHalos
Project-URL: issues, https://github.com/Santiq22/FermiHalos/issues
Keywords: astrophysics,dark matter,halo,RAR
Requires-Python: >=3.10
License-File: LICENSE
Requires-Dist: numpy>=1.23.5
Requires-Dist: scipy>=1.15.0
Dynamic: author
Dynamic: home-page
Dynamic: license-file
Dynamic: requires-python
